sagemcom_f3896lg_zg_api/__about__.py
sagemcom_f3896lg_zg_api/__init__.py
sagemcom_f3896lg_zg_api/__main__.py
sagemcom_f3896lg_zg_api/client.py
sagemcom_f3896lg_zg_api/model.py
sagemcom_f3896lg_zg_api-0.1.0.dist-info/METADATA
sagemcom_f3896lg_zg_api-0.1.0.dist-info/WHEEL
sagemcom_f3896lg_zg_api-0.1.0.dist-info/licenses/LICENSE.txt
sagemcom_f3896lg_zg_api-0.1.0.dist-info/RECORD
