Metadata-Version: 2.3
Name: sagemcom-f3896lg-zg-api
Version: 0.1.0
Project-URL: Documentation, https://github.com/mgyucht/sagemcom-f3896lg-zg-api#readme
Project-URL: Issues, https://github.com/mgyucht/sagemcom-f3896lg-zg-api/issues
Project-URL: Source, https://github.com/mgyucht/sagemcom-f3896lg-zg-api
Author-email: Miles Yucht <mgyucht@gmail.com>
License-Expression: MIT
License-File: LICENSE.txt
Classifier: Development Status :: 4 - Beta
Classifier: Programming Language :: Python
Classifier: Programming Language :: Python :: 3.8
Classifier: Programming Language :: Python :: 3.9
Classifier: Programming Language :: Python :: 3.10
Classifier: Programming Language :: Python :: 3.11
Classifier: Programming Language :: Python :: 3.12
Classifier: Programming Language :: Python :: Implementation :: CPython
Classifier: Programming Language :: Python :: Implementation :: PyPy
Requires-Python: >=3.8
Requires-Dist: aiohttp==3.10.10
Requires-Dist: pydantic==2.9.2
